kivy_garden/splittergrid/__init__.py
kivy_garden/splittergrid/_version.py
kivy_garden/splittergrid/tests/test_import.py
kivy_garden.splittergrid-1.0.dist-info/AUTHORS.txt
kivy_garden.splittergrid-1.0.dist-info/LICENSE.txt
kivy_garden.splittergrid-1.0.dist-info/METADATA
kivy_garden.splittergrid-1.0.dist-info/WHEEL
kivy_garden.splittergrid-1.0.dist-info/top_level.txt
kivy_garden.splittergrid-1.0.dist-info/RECORD
